Metadata-Version: 2.1
Name: iqscli
Version: 0.4
Summary: iqscli is an unofficial CLI for IBM Quantum Systems
Home-page: https://github.com/metebalci/iqscli
Author: Mete Balci
Author-email: metebalci@gmail.com
License: GPLv3
Keywords: cli ibm quantum
Platform: UNKNOWN
Classifier: Environment :: Console
Classifier: License :: OSI Approved :: GNU General Public License v3 (GPLv3)
Classifier: Topic :: Utilities
Classifier: Programming Language :: Python :: 3
License-File: LICENSE
